roi2bb/__init__.py
roi2bb/converter.py
roi2bb/utils.py
roi2bb-0.1.0.dist-info/licenses/LICENSE
roi2bb-0.1.0.dist-info/METADATA
roi2bb-0.1.0.dist-info/WHEEL
roi2bb-0.1.0.dist-info/entry_points.txt
roi2bb-0.1.0.dist-info/top_level.txt
roi2bb-0.1.0.dist-info/RECORD
