Metadata-Version: 2.4
Name: roi2bb
Version: 0.1.0
Summary: 3D Slicer ROI to YOLO Bounding Box Coordinates Converter for Medical Imaging
Author-email: Elham Mahmoudi <mahmoudi.elham91@gmail.com>
Maintainer-email: Elham Mahmoudi <mahmoudi.elham91@gmail.com>
License: MIT
Project-URL: Homepage, https://github.com/elimah91/roi2bb
Project-URL: Repository, https://github.com/elimah91/roi2bb.git
Project-URL: Issues, https://github.com/elimah91/roi2bb/issues
Project-URL: Documentation, https://github.com/elimah91/roi2bb#readme
Keywords: medical-imaging,3d-slicer,yolo,bounding-box,roi,deep-learning,computer-vision
Classifier: Development Status :: 3 - Alpha
Classifier: Intended Audience :: Developers
Classifier: Intended Audience :: Science/Research
Classifier: License :: OSI Approved :: MIT License
Classifier: Programming Language :: Python :: 3
Classifier: Programming Language :: Python :: 3.7
Classifier: Programming Language :: Python :: 3.8
Classifier: Programming Language :: Python :: 3.9
Classifier: Programming Language :: Python :: 3.10
Classifier: Programming Language :: Python :: 3.11
Classifier: Programming Language :: Python :: 3.12
Classifier: Topic :: Scientific/Engineering :: Medical Science Apps.
Classifier: Topic :: Software Development :: Libraries :: Python Modules
Requires-Python: >=3.7
License-File: LICENSE
Requires-Dist: numpy>=1.19.0
Requires-Dist: nibabel>=3.2.0
Provides-Extra: all
Requires-Dist: pandas>=1.3.0; extra == "all"
Requires-Dist: opencv-python>=4.5.0; extra == "all"
Requires-Dist: pydicom>=2.2.0; extra == "all"
Requires-Dist: Pillow>=8.0.0; extra == "all"
Requires-Dist: SimpleITK>=2.1.0; extra == "all"
Provides-Extra: dev
Requires-Dist: pytest>=6.0.0; extra == "dev"
Requires-Dist: pytest-cov>=2.12.0; extra == "dev"
Requires-Dist: black>=21.0.0; extra == "dev"
Requires-Dist: flake8>=3.9.0; extra == "dev"
Requires-Dist: mypy>=0.910; extra == "dev"
Dynamic: license-file
Dynamic: requires-python
